LICENSE
README.md
setup.py
promptimal/__init__.py
promptimal/__main__.py
promptimal/app.py
promptimal/promptimal.py
promptimal.egg-info/PKG-INFO
promptimal.egg-info/SOURCES.txt
promptimal.egg-info/dependency_links.txt
promptimal.egg-info/entry_points.txt
promptimal.egg-info/requires.txt
promptimal.egg-info/top_level.txt
promptimal/dtos/ProgressStep.py
promptimal/dtos/PromptCandidate.py
promptimal/dtos/TokenCount.py
promptimal/dtos/__init__.py
promptimal/optimizer/__init__.py
promptimal/optimizer/main.py
promptimal/optimizer/prompts.py
promptimal/optimizer/utils.py