Metadata-Version: 2.1
Name: promptimal
Version: 1.0.2
Summary: A dead-simple prompt optimizer
Home-page: https://github.com/shobrook/promptimal
Author: shobrook
Author-email: shobrookj@gmail.com
License: MIT
Keywords: prompt optimizer openai prompt-tuning prompt-engineering prompt-optimization genetic-algorithms
Requires-Python: >=3
License-File: LICENSE
Requires-Dist: json-repair
Requires-Dist: pyperclip
Requires-Dist: openai
Requires-Dist: urwid
